aws_cost_optimization_3/__init__.py
aws_cost_optimization_3/utils.py
aws_cost_optimization_3-0.1.6.dist-info/LICENCE
aws_cost_optimization_3-0.1.6.dist-info/METADATA
aws_cost_optimization_3-0.1.6.dist-info/WHEEL
aws_cost_optimization_3-0.1.6.dist-info/top_level.txt
aws_cost_optimization_3-0.1.6.dist-info/RECORD
